kpireport_smtp/__init__.py
kpireport_smtp/output.py
kpireport_smtp-0.0.1.dist-info/METADATA
kpireport_smtp-0.0.1.dist-info/WHEEL
kpireport_smtp-0.0.1.dist-info/entry_points.txt
kpireport_smtp-0.0.1.dist-info/top_level.txt
kpireport_smtp-0.0.1.dist-info/RECORD
